pdf_parser/__init__.py
pdf_parser/parser.py
pdf_heading_parser-0.1.0.dist-info/METADATA
pdf_heading_parser-0.1.0.dist-info/WHEEL
pdf_heading_parser-0.1.0.dist-info/entry_points.txt
pdf_heading_parser-0.1.0.dist-info/top_level.txt
pdf_heading_parser-0.1.0.dist-info/RECORD
